processamento_de_imagem_em_python_desafio_dio/__init__.py
processamento_de_imagem_em_python_desafio_dio/processamento/__init__.py
processamento_de_imagem_em_python_desafio_dio/processamento/combinacao.py
processamento_de_imagem_em_python_desafio_dio/processamento/transformacao.py
processamento_de_imagem_em_python_desafio_dio/utils/__init__.py
processamento_de_imagem_em_python_desafio_dio/utils/io.py
processamento_de_imagem_em_python_desafio_dio/utils/plot.py
processamento_de_imagem_em_python_desafio_dio-0.0.5.dist-info/METADATA
processamento_de_imagem_em_python_desafio_dio-0.0.5.dist-info/WHEEL
processamento_de_imagem_em_python_desafio_dio-0.0.5.dist-info/top_level.txt
processamento_de_imagem_em_python_desafio_dio-0.0.5.dist-info/RECORD
