Metadata-Version: 2.1
Name: processamento_de_imagem_em_python_desafio_dio
Version: 0.0.5
Summary: Image Processing Package using skimage
Home-page: https://github.com/joaodatapaulo/criando-um-pacote-de-processamento-de-imagem-com-python
Author: João Paulo
Requires-Python: >=3.8
Requires-Dist: matplotlib
Requires-Dist: numpy
Requires-Dist: scikit-image>=0.16.1
